mp3tools/__init__.py
mp3tools/__main__.py
mp3tools/base.py
mp3tools/cli.py
mp3tools/mp3tool.py
mp3tools-1.2.3.dist-info/licenses/LICENSE
mp3tools-1.2.3.dist-info/METADATA
mp3tools-1.2.3.dist-info/WHEEL
mp3tools-1.2.3.dist-info/entry_points.txt
mp3tools-1.2.3.dist-info/top_level.txt
mp3tools-1.2.3.dist-info/RECORD
