Metadata-Version: 2.4
Name: mp3tools
Version: 1.2.3
Summary: Awesome mp3tools created by carsten-engelke
Home-page: https://github.com/carsten-engelke/mp3tools/
Author: carsten-engelke
License-File: LICENSE
Requires-Dist: autopep8>=1
Requires-Dist: pycodestyle>=2
Requires-Dist: pynput>=1
Requires-Dist: six>=1
Provides-Extra: test
Requires-Dist: pytest; extra == "test"
Requires-Dist: coverage; extra == "test"
Requires-Dist: flake8; extra == "test"
Requires-Dist: black; extra == "test"
Requires-Dist: isort; extra == "test"
Requires-Dist: pytest-cov; extra == "test"
Requires-Dist: mypy; extra == "test"
Requires-Dist: gitchangelog; extra == "test"
Requires-Dist: mkdocs; extra == "test"
Dynamic: author
Dynamic: description
Dynamic: description-content-type
Dynamic: home-page
Dynamic: license-file
Dynamic: provides-extra
Dynamic: requires-dist
Dynamic: summary
